flask_richtexteditor/__init__.py
flask_richtexteditor-0.0.1.dev0.dist-info/LICENSE
flask_richtexteditor-0.0.1.dev0.dist-info/METADATA
flask_richtexteditor-0.0.1.dev0.dist-info/WHEEL
flask_richtexteditor-0.0.1.dev0.dist-info/top_level.txt
flask_richtexteditor-0.0.1.dev0.dist-info/RECORD
