Metadata-Version: 2.1
Name: flask-richtexteditor
Version: 0.0.1.dev0
Summary: Flask Rich Text Editor
Home-page: https://github.com/cizario/flask-richtexteditor/
Author: Nizar DELLELI
Author-email: nizar.delleli@gmail.com
License: BSD 3-Clause
Project-URL: Documentation, https://github.com/cizario/flask-richtexteditor/
Project-URL: Release notes, https://github.com/cizario/flask-richtexteditor/
Project-URL: Funding, https://github.com/cizario/flask-richtexteditor/
Project-URL: Source, https://github.com/cizario/flask-richtexteditor/
Project-URL: Tracker, https://github.com/cizario/flask-richtexteditor/issues
Keywords: flask richtext editor ckeditor tinymce markdown reStructruedText wysiwyg
Platform: UNKNOWN
Classifier: Development Status :: 1 - Planning
Classifier: Environment :: Web Environment
Classifier: Framework :: Flask
Classifier: Intended Audience :: Developers
Classifier: License :: OSI Approved :: BSD License
Classifier: Natural Language :: English
Classifier: Operating System :: OS Independent
Classifier: Programming Language :: Python
Classifier: Programming Language :: Python :: 3
Classifier: Programming Language :: Python :: 3 :: Only
Classifier: Programming Language :: Python :: 3.6
Classifier: Programming Language :: Python :: 3.7
Classifier: Programming Language :: Python :: 3.8
Classifier: Topic :: Internet :: WWW/HTTP
Classifier: Topic :: Internet :: WWW/HTTP :: Dynamic Content
Requires-Python: >=3.6
